traceai_mcp/__init__.py
traceai_mcp/package.py
traceai_mcp/version.py
traceai_mcp-0.1.1.dist-info/METADATA
traceai_mcp-0.1.1.dist-info/WHEEL
traceai_mcp-0.1.1.dist-info/RECORD
