Metadata-Version: 2.3
Name: traceAI-mcp
Version: 0.1.1
Summary: OpenTelemetry instrumentation for MCP
Author: Future AGI
Author-email: no-reply@futureagi.com
Requires-Python: >3.10,<3.14
Classifier: Programming Language :: Python :: 3
Classifier: Programming Language :: Python :: 3.11
Classifier: Programming Language :: Python :: 3.12
Classifier: Programming Language :: Python :: 3.13
Requires-Dist: fi-instrumentation-otel (>=0.1.11)
Requires-Dist: mcp (>=1.8.1)
